{
    "balance_change": {
        "balanceChanges": [
            {
                "account": "0x744e69fa4c20b439e2f8a1d0b96c28f9a8ef51b7",
                "assets": [
                    {
                        "address": "0xeeeeeeeeeeeeeeeeeeeeeeeeeeeeeeeeeeeeeeee",
                        "amount": "0.007695",
                        "iconUrl": "https://assets.blocksec.com/image/1663669189317-3.png",
                        "isERC1155": false,
                        "isERC721": false,
                        "sign": false,
                        "value": "11.8759243499999994405"
                    }
                ]
            },
            {
                "account": "0x445018d5cc377fceec634baddf7fdc9289b55ed7",
                "assets": [
                    {
                        "address": "0xeeeeeeeeeeeeeeeeeeeeeeeeeeeeeeeeeeeeeeee",
                        "amount": "0.007695",
                        "iconUrl": "https://assets.blocksec.com/image/1663669189317-3.png",
                        "isERC1155": false,
                        "isERC721": false,
                        "sign": true,
                        "value": "11.8759243499999994405"
                    }
                ]
            }
        ]
    },
    "profile": {
        "basic_info": {
            "baseFee": "256.379032748",
            "blockNumber": 18114982,
            "callData": "0x",
            "debugEnable": true,
            "errorInfo": "",
            "eventCount": 0,
            "feeRecipient": "0x4675c7e5baafbffbca748158becba61ef3b0a263",
            "formatValue": "0.007695",
            "gasLimit": 21000,
            "gasPrice": "258.15202756",
            "gasUsed": 21000,
            "intTxnCount": 0,
            "internalRevert": false,
            "internalRevertMessage": "",
            "isContractCreation": false,
            "isFlashloan": false,
            "maxFee": "318.726023628",
            "nonce": 0,
            "overwritedBlockNumber": -1,
            "priorityFee": "1.772994812",
            "receiver": "0x445018d5cc377fceec634baddf7fdc9289b55ed7",
            "revertMessage": "",
            "sender": "0x744e69fa4c20b439e2f8a1d0b96c28f9a8ef51b7",
            "simulationEnable": true,
            "sourceTxnHash": "0x64236174c4dd7d837d845ef0b8096ba0476bc1ddfda677c620ef4e55376daaea",
            "status": true,
            "timestamp": "2023-09-11T18:45:23Z",
            "transactionFee": "0.00542119257876",
            "txnHash": "0x64236174c4dd7d837d845ef0b8096ba0476bc1ddfda677c620ef4e55376daaea",
            "txnIndex": 90,
            "type": 2,
            "value": "7695000000000000"
        },
        "fund_flow": [
            {
                "amount": "0.007695",
                "from": "0x744e69fa4c20b439e2f8a1d0b96c28f9a8ef51b7",
                "id": 1,
                "isERC1155": false,
                "isERC721": false,
                "isReverted": false,
                "order": 1,
                "to": "0x445018d5cc377fceec634baddf7fdc9289b55ed7",
                "token": "0xeeeeeeeeeeeeeeeeeeeeeeeeeeeeeeeeeeeeeeee"
            }
        ],
        "token_infos": [
            {
                "address": "0xc02aaa39b223fe8d0a0e5c4f27ead9083c756cc2",
                "decimals": 18
            },
            {
                "address": "0xeeeeeeeeeeeeeeeeeeeeeeeeeeeeeeeeeeeeeeee",
                "decimals": 18
            }
        ]
    },
    "address_label": {
        "labels": [
            {
                "address": "0x0000000000000000000000000000000000000004",
                "label": "Precompiled"
            },
            {
                "address": "0xeeeeeeeeeeeeeeeeeeeeeeeeeeeeeeeeeeeeeeee",
                "label": "Ether"
            },
            {
                "address": "0x0000000000000000000000000000000000000001",
                "label": "Precompiled"
            },
            {
                "address": "0x0000000000000000000000000000000000000002",
                "label": "Precompiled"
            },
            {
                "address": "0x0000000000000000000000000000000000000003",
                "label": "Precompiled"
            }
        ]
    },
    "trace": {
        "accountLabels": null,
        "dataMap": {
            "-1": {
                "invocation": {
                    "address": "0x744e69fa4c20b439e2f8a1d0b96c28f9a8ef51b7",
                    "callData": "",
                    "decodedMethod": null,
                    "errorInfo": "",
                    "fromAddress": "",
                    "gasUsed": 0,
                    "id": -1,
                    "methodDecoded": false,
                    "operation": "",
                    "output": "",
                    "revert": false,
                    "revertMessage": "",
                    "selector": "",
                    "status": false,
                    "value": ""
                },
                "nodeType": 0
            },
            "0": {
                "invocation": {
                    "address": "0x445018d5cc377fceec634baddf7fdc9289b55ed7",
                    "callData": "0x",
                    "decodedMethod": null,
                    "errorInfo": "",
                    "fromAddress": "0x744e69fa4c20b439e2f8a1d0b96c28f9a8ef51b7",
                    "gasUsed": 21000,
                    "id": 0,
                    "methodDecoded": false,
                    "operation": "CALL",
                    "output": "",
                    "revert": false,
                    "revertMessage": "",
                    "selector": "fallback",
                    "status": true,
                    "value": "0.007695"
                },
                "nodeType": 0
            }
        },
        "gasFlame": [
            {
                "children": [
                    {
                        "children": [
                            {
                                "children": [],
                                "depth": 0,
                                "name": "Initial Gas",
                                "value": 21000
                            },
                            {
                                "children": [],
                                "depth": 0,
                                "name": "Executed Gas",
                                "value": 0
                            }
                        ],
                        "depth": -1,
                        "name": "Actual Gas Used",
                        "value": 21000
                    },
                    {
                        "children": [],
                        "depth": -1,
                        "name": "Refunded Gas",
                        "value": 0
                    }
                ],
                "depth": -2,
                "name": "Total Gas",
                "value": 21000
            }
        ],
        "isConfirmed": true,
        "mainTrace": [
            {
                "children": [
                    {
                        "children": [],
                        "depth": 0,
                        "id": 0,
                        "order": 0
                    }
                ],
                "depth": -1,
                "id": -1,
                "order": -1
            }
        ],
        "mainTraceNodeCount": 1,
        "parentIdMap": {
            "0": -1
        },
        "tidyTrace": [
            {
                "children": [
                    {
                        "children": [],
                        "depth": 0,
                        "id": 0,
                        "order": 0
                    }
                ],
                "depth": -1,
                "id": -1,
                "order": -1
            }
        ],
        "tidyTraceNodeCount": 1
    },
    "state_change": {
        "stateChanges": []
    }
}