{
    "balance_change": {
        "balanceChanges": [
            {
                "account": "0x0da6fe1e9e1521bacd1c458932e778ed2b08d1e2",
                "assets": [
                    {
                        "address": "0xeeeeeeeeeeeeeeeeeeeeeeeeeeeeeeeeeeeeeeee",
                        "amount": "90",
                        "iconUrl": "https://assets.blocksec.com/image/1663669189317-3.png",
                        "isERC1155": false,
                        "isERC721": false,
                        "sign": false,
                        "value": ""
                    }
                ]
            },
            {
                "account": "0x432d8c1a4a18e63b09b4331e044d270c4d819d66",
                "assets": [
                    {
                        "address": "0xeeeeeeeeeeeeeeeeeeeeeeeeeeeeeeeeeeeeeeee",
                        "amount": "90",
                        "iconUrl": "https://assets.blocksec.com/image/1663669189317-3.png",
                        "isERC1155": false,
                        "isERC721": false,
                        "sign": true,
                        "value": ""
                    }
                ]
            }
        ]
    },
    "profile": {
        "basic_info": {
            "baseFee": "",
            "blockNumber": 4186925,
            "callData": "0x",
            "debugEnable": true,
            "errorInfo": "",
            "eventCount": 0,
            "feeRecipient": "0x4bb96091ee9d802ed039c4d1a5f6216f90f81b01",
            "formatValue": "90",
            "gasLimit": 250000,
            "gasPrice": "23.1",
            "gasUsed": 21051,
            "intTxnCount": 0,
            "internalRevert": false,
            "internalRevertMessage": "",
            "isContractCreation": false,
            "isFlashloan": false,
            "maxFee": "",
            "nonce": 57,
            "overwritedBlockNumber": -1,
            "priorityFee": "",
            "receiver": "0x432d8c1a4a18e63b09b4331e044d270c4d819d66",
            "revertMessage": "",
            "sender": "0x0da6fe1e9e1521bacd1c458932e778ed2b08d1e2",
            "simulationEnable": true,
            "sourceTxnHash": "0x8018e5e4c69fd25871cc53c5a76a0a7c195d2f8aa9a04e0ba334c963e7cef486",
            "status": true,
            "timestamp": "2017-08-21T18:36:44Z",
            "transactionFee": "0.0004862781",
            "txnHash": "0x8018e5e4c69fd25871cc53c5a76a0a7c195d2f8aa9a04e0ba334c963e7cef486",
            "txnIndex": 22,
            "type": 0,
            "value": "90000000000000000000"
        },
        "fund_flow": [
            {
                "amount": "90",
                "from": "0x0da6fe1e9e1521bacd1c458932e778ed2b08d1e2",
                "id": 1,
                "isERC1155": false,
                "isERC721": false,
                "isReverted": false,
                "order": 1,
                "to": "0x432d8c1a4a18e63b09b4331e044d270c4d819d66",
                "token": "0xeeeeeeeeeeeeeeeeeeeeeeeeeeeeeeeeeeeeeeee"
            }
        ],
        "token_infos": [
            {
                "address": "0xc02aaa39b223fe8d0a0e5c4f27ead9083c756cc2",
                "decimals": 18
            },
            {
                "address": "0xeeeeeeeeeeeeeeeeeeeeeeeeeeeeeeeeeeeeeeee",
                "decimals": 18
            }
        ]
    },
    "address_label": {
        "labels": [
            {
                "address": "0x0000000000000000000000000000000000000001",
                "label": "Precompiled"
            },
            {
                "address": "0x0000000000000000000000000000000000000002",
                "label": "Precompiled"
            },
            {
                "address": "0x0000000000000000000000000000000000000003",
                "label": "Precompiled"
            },
            {
                "address": "0x0000000000000000000000000000000000000004",
                "label": "Precompiled"
            },
            {
                "address": "0xeeeeeeeeeeeeeeeeeeeeeeeeeeeeeeeeeeeeeeee",
                "label": "Ether"
            },
            {
                "address": "0x432d8c1a4a18e63b09b4331e044d270c4d819d66",
                "label": "BITTREX"
            }
        ]
    },
    "trace": {
        "accountLabels": null,
        "dataMap": {
            "-1": {
                "invocation": {
                    "address": "0x0da6fe1e9e1521bacd1c458932e778ed2b08d1e2",
                    "callData": "",
                    "decodedMethod": null,
                    "errorInfo": "",
                    "fromAddress": "",
                    "gasUsed": 0,
                    "id": -1,
                    "methodDecoded": false,
                    "operation": "",
                    "output": "",
                    "revert": false,
                    "revertMessage": "",
                    "selector": "",
                    "status": false,
                    "value": ""
                },
                "nodeType": 0
            },
            "0": {
                "invocation": {
                    "address": "0x432d8c1a4a18e63b09b4331e044d270c4d819d66",
                    "callData": "0x",
                    "decodedMethod": null,
                    "errorInfo": "",
                    "fromAddress": "0x0da6fe1e9e1521bacd1c458932e778ed2b08d1e2",
                    "gasUsed": 21051,
                    "id": 0,
                    "methodDecoded": false,
                    "operation": "CALL",
                    "output": "",
                    "revert": false,
                    "revertMessage": "",
                    "selector": "fallback",
                    "status": true,
                    "value": "90"
                },
                "nodeType": 0
            }
        },
        "gasFlame": [
            {
                "children": [
                    {
                        "children": [
                            {
                                "children": [],
                                "depth": 0,
                                "name": "Initial Gas",
                                "value": 21000
                            },
                            {
                                "children": [],
                                "depth": 0,
                                "name": "Executed Gas",
                                "value": 51
                            }
                        ],
                        "depth": -1,
                        "name": "Actual Gas Used",
                        "value": 21051
                    },
                    {
                        "children": [],
                        "depth": -1,
                        "name": "Refunded Gas",
                        "value": 0
                    }
                ],
                "depth": -2,
                "name": "Total Gas",
                "value": 21051
            }
        ],
        "isConfirmed": true,
        "mainTrace": [
            {
                "children": [
                    {
                        "children": [],
                        "depth": 0,
                        "id": 0,
                        "order": 0
                    }
                ],
                "depth": -1,
                "id": -1,
                "order": -1
            }
        ],
        "mainTraceNodeCount": 1,
        "parentIdMap": {
            "0": -1
        },
        "tidyTrace": [
            {
                "children": [
                    {
                        "children": [],
                        "depth": 0,
                        "id": 0,
                        "order": 0
                    }
                ],
                "depth": -1,
                "id": -1,
                "order": -1
            }
        ],
        "tidyTraceNodeCount": 1
    },
    "state_change": {
        "stateChanges": []
    }
}